django_silver-0.2.2.dist-info/DESCRIPTION.rst
django_silver-0.2.2.dist-info/METADATA
django_silver-0.2.2.dist-info/RECORD
django_silver-0.2.2.dist-info/WHEEL
django_silver-0.2.2.dist-info/metadata.json
django_silver-0.2.2.dist-info/top_level.txt
silver/.DS_Store
silver/__init__.py
silver/_version.py
silver/admin.py
silver/currencies.py
silver/documents_generator.py
silver/urls.py
silver/validators.py
silver/views.py
silver/api/__init__.py
silver/api/exceptions.py
silver/api/filters.py
silver/api/pagination.py
silver/api/serializers.py
silver/api/urls.py
silver/api/views.py
silver/fixtures/initial_dev_data.json
silver/management/__init__.py
silver/management/commands/__init__.py
silver/management/commands/execute_transactions.py
silver/management/commands/fetch_transactions_status.py
silver/management/commands/generate_docs.py
silver/management/commands/tweak_billing_log.py
silver/migrations/.DS_Store
silver/migrations/0001_initial.py
silver/migrations/0002_auto_20150416_1009.py
silver/migrations/0003_auto_20150417_0634.py
silver/migrations/0004_auto_20150429_1731.py
silver/migrations/0005_auto_20150429_1732.py
silver/migrations/0006_auto_20150430_1457.py
silver/migrations/0007_auto_20150430_1549.py
silver/migrations/0008_auto_20150430_1804.py
silver/migrations/0009_auto_20150717_1428.py
silver/migrations/0031_auto_20170125_1343.py
silver/migrations/0032_auto_20170201_1342.py
silver/migrations/0033_auto_20170203_1540.py
silver/migrations/0034_auto_20170203_1644.py
silver/migrations/__init__.py
silver/models/__init__.py
silver/models/payment_methods.py
silver/models/plans.py
silver/models/product_codes.py
silver/models/subscriptions.py
silver/models/billing_entities/__init__.py
silver/models/billing_entities/base.py
silver/models/billing_entities/customer.py
silver/models/billing_entities/provider.py
silver/models/documents/__init__.py
silver/models/documents/base.py
silver/models/documents/document.py
silver/models/documents/entries.py
silver/models/documents/invoice.py
silver/models/documents/proforma.py
silver/models/transactions/__init__.py
silver/models/transactions/codes.py
silver/models/transactions/transaction.py
