Metadata-Version: 2.0
Name: django-silver
Version: 0.2.2
Summary: Django app for automated billing with an API.
Requires-Dist: PyJWT
Requires-Dist: PyPDF2
Requires-Dist: cryptography (==1.7.1)
Requires-Dist: django (<1.9)
Requires-Dist: django-annoying
Requires-Dist: django-autocomplete-light (==3.2.1)
Requires-Dist: django-filter (==0.15.3)
Requires-Dist: django-fsm (>=2.3.0)
Requires-Dist: django-jsonfield (==0.9.15)
Requires-Dist: django-livefield
Requires-Dist: django-model-utils
Requires-Dist: django-xhtml2pdf
Requires-Dist: djangorestframework (>=3.3.0)
Requires-Dist: djangorestframework-bulk
Requires-Dist: furl
Requires-Dist: html5lib (==0.999)
Requires-Dist: pycountry (>=16.11.08)
Requires-Dist: python-dateutil
Requires-Dist: pytz
Requires-Dist: pyvat
Requires-Dist: sqlparse (==0.2.2)
Requires-Dist: xhtml2pdf
